syslogcef/__init__.py
syslogcef/__version__.py
syslogcef/testmessages.py
tests/__init__.py
tests/test_syslogcef.py
syslogcef-0.1.8.dist-info/LICENSE
syslogcef-0.1.8.dist-info/METADATA
syslogcef-0.1.8.dist-info/WHEEL
syslogcef-0.1.8.dist-info/top_level.txt
syslogcef-0.1.8.dist-info/RECORD
