Metadata-Version: 2.1
Name: syslogcef
Version: 0.1.8
Summary: Python library to easily send CEF formatted messages to syslog server
Home-page: https://github.com/tristanlatr/syslogcef
License: MIT License
Keywords: syslog cef
Classifier: Programming Language :: Python :: 3
Requires-Python: >=3.6
License-File: LICENSE
Requires-Dist: rfc5424-logging-handler
Requires-Dist: cefevent (>=0.5.3)
Provides-Extra: dev
Requires-Dist: tox ; extra == 'dev'
